dyrkdevice/__init__.py
dyrkdevice/basicDyrkDevice.py
dyrkdevice-0.1.0.dist-info/LICENSE
dyrkdevice-0.1.0.dist-info/METADATA
dyrkdevice-0.1.0.dist-info/WHEEL
dyrkdevice-0.1.0.dist-info/top_level.txt
dyrkdevice-0.1.0.dist-info/RECORD
