Metadata-Version: 2.1
Name: dyrkdevice
Version: 0.1.0
Summary: Library for implementing a dyrk device
Home-page: https://dyrk.io
Author: Dyrk
Author-email: bok.will@gmail.com
License: UNKNOWN
Project-URL: Source, https://gitlab.com/dyrk/device/dyrkdevice/
Platform: UNKNOWN
Classifier: Programming Language :: Python :: 3
Classifier: License :: OSI Approved :: GNU General Public License v3 (GPLv3)
Classifier: Operating System :: OS Independent
Requires-Python: >=3.9
License-File: LICENSE
Requires-Dist: pyyaml (>=5.4.1)
Requires-Dist: paho-mqtt (>=1.5.1)
